acceptance_tests/__init__.py
acceptance_tests/conftest.py
acceptance_tests/i18n_test.py
acceptance_tests/model_test.py
acceptance_tests/url_test.py
acceptance_tests/admin/__init__.py
acceptance_tests/admin/issue_test.py
acceptance_tests/private/__init__.py
acceptance_tests/private/issue_test.py
acceptance_tests/public/__init__.py
acceptance_tests/public/categories_test.py
acceptance_tests/public/issue_test.py
getitfixed/__init__.py
getitfixed/i18n.py
getitfixed/lingua_extractor.py
getitfixed/loader.py
getitfixed/pshell.py
getitfixed/routes.py
getitfixed/subscribers.py
getitfixed/url.py
getitfixed/alembic/env.py
getitfixed/alembic/script.py.mako
getitfixed/alembic/versions/007ce1ec46f8_increase_email_fields_length_to_254_.py
getitfixed/alembic/versions/0b12402a098e_first_migration.py
getitfixed/alembic/versions/2fdd37d28068_remove_notnull_on_some_fields.py
getitfixed/alembic/versions/6d8c64186efa_add_field_issue_private.py
getitfixed/alembic/versions/73e05f3650a7_add_field_photo_hash.py
getitfixed/alembic/versions/c58f6490f52e_remove_mandatory_on_issue_localisation.py
getitfixed/alembic/versions/f12edd1058e7_add_field_type_wms_layer.py
getitfixed/emails/__init__.py
getitfixed/emails/email_service.py
getitfixed/locale/de/LC_MESSAGES/getitfixed.mo
getitfixed/locale/fr/LC_MESSAGES/getitfixed.mo
getitfixed/models/__init__.py
getitfixed/models/getitfixed.py
getitfixed/models/meta.py
getitfixed/scripts/__init__.py
getitfixed/scripts/setup_test_data.py
getitfixed/static/epsg-21781.js
getitfixed/static/favicon.ico
getitfixed/static/theme.css
getitfixed/static/icons/cat-default.png
getitfixed/static/icons/gif-black.png
getitfixed/static/icons/gif-green.png
getitfixed/static/icons/gif-red.png
getitfixed/static/lib/bootstrap/dist/css/bootstrap.min.css
getitfixed/static/lib/bootstrap/dist/fonts/glyphicons-halflings-regular.ttf
getitfixed/static/lib/bootstrap/dist/fonts/glyphicons-halflings-regular.woff2
getitfixed/static/lib/bootstrap/dist/js/bootstrap.min.js
getitfixed-1.0.29.dist-info/LICENSE
getitfixed-1.0.29.dist-info/METADATA
getitfixed-1.0.29.dist-info/WHEEL
getitfixed-1.0.29.dist-info/entry_points.txt
getitfixed-1.0.29.dist-info/top_level.txt
getitfixed-1.0.29.dist-info/RECORD
