Metadata-Version: 2.1
Name: getitfixed
Version: 1.0.29
Summary: getitfixed
Home-page: UNKNOWN
Author: 
Author-email: 
License: UNKNOWN
Keywords: web wsgi bfg pylons pyramid
Platform: UNKNOWN
Classifier: Programming Language :: Python
Classifier: Programming Language :: Python :: 3
Classifier: Framework :: Pyramid
Classifier: Topic :: Internet :: WWW/HTTP
Classifier: Topic :: Internet :: WWW/HTTP :: WSGI :: Application
License-File: LICENSE
Requires-Dist: alembic
Requires-Dist: c2c.template
Requires-Dist: c2cgeoform (>=2.1.17)
Requires-Dist: beaker-redis
Requires-Dist: plaster-pastedeploy
Requires-Dist: psycopg2-binary
Requires-Dist: pyramid-tm
Requires-Dist: transaction
Requires-Dist: waitress
Requires-Dist: deform (>=2.0.10)
Requires-Dist: SQLAlchemy (>=1.1.13)
